sd_material_ui/Accordion.py
sd_material_ui/AppBar.py
sd_material_ui/AutoComplete.py
sd_material_ui/BottomNavigation.py
sd_material_ui/Button.py
sd_material_ui/Card.py
sd_material_ui/Checkbox.py
sd_material_ui/CircularProgress.py
sd_material_ui/CollapseTransition.py
sd_material_ui/Dialog.py
sd_material_ui/Divider.py
sd_material_ui/Drawer.py
sd_material_ui/DropDownMenu.py
sd_material_ui/FadeTransition.py
sd_material_ui/FlatButton.py
sd_material_ui/FontIcon.py
sd_material_ui/GrowTransition.py
sd_material_ui/IconButton.py
sd_material_ui/LinearBuffer.py
sd_material_ui/LinearDeterminate.py
sd_material_ui/LinearIndeterminate.py
sd_material_ui/Pagination.py
sd_material_ui/Paper.py
sd_material_ui/Picker.py
sd_material_ui/Popover.py
sd_material_ui/Questions.py
sd_material_ui/QuestionsTabs.py
sd_material_ui/RadioButtonGroup.py
sd_material_ui/RaisedButton.py
sd_material_ui/SlideTransition.py
sd_material_ui/Snackbar.py
sd_material_ui/Stepper.py
sd_material_ui/Subheader.py
sd_material_ui/Tabs.py
sd_material_ui/Toggle.py
sd_material_ui/Toolbar.py
sd_material_ui/Tooltip.py
sd_material_ui/ZoomTransition.py
sd_material_ui/__init__.py
sd_material_ui/_imports_.py
sd_material_ui/metadata.json
sd_material_ui/package.json
sd_material_ui/sd_material_ui.dev.js
sd_material_ui/sd_material_ui.min.js
sd_material_ui/sdmaterialui.py
sd_material_ui-4.6.0.dist-info/LICENSE.txt
sd_material_ui-4.6.0.dist-info/METADATA
sd_material_ui-4.6.0.dist-info/WHEEL
sd_material_ui-4.6.0.dist-info/top_level.txt
sd_material_ui-4.6.0.dist-info/RECORD
