Metadata-Version: 2.1
Name: sd-material-ui
Version: 4.6.0
Summary: material-ui components for Dash
Home-page: UNKNOWN
Author: Michael Clawar, Eric Linden, Sreeja Keesara, Danny Kaminsky tech@stratodem.com
License: MIT
Platform: UNKNOWN
License-File: LICENSE.txt
